official/__init__.py
official/common/__init__.py
official/common/dataset_fn.py
official/common/distribute_utils.py
official/common/distribute_utils_test.py
official/common/flags.py
official/common/registry_imports.py
official/common/streamz_counters.py
official/core/__init__.py
official/core/actions.py
official/core/actions_test.py
official/core/base_task.py
official/core/base_trainer.py
official/core/base_trainer_test.py
official/core/config_definitions.py
official/core/exp_factory.py
official/core/export_base.py
official/core/export_base_test.py
official/core/file_writers.py
official/core/file_writers_test.py
official/core/input_reader.py
official/core/registry.py
official/core/registry_test.py
official/core/savedmodel_checkpoint_manager.py
official/core/savedmodel_checkpoint_manager_test.py
official/core/task_factory.py
official/core/test_utils.py
official/core/tf_example_builder.py
official/core/tf_example_builder_test.py
official/core/tf_example_feature_key.py
official/core/tf_example_feature_key_test.py
official/core/train_lib.py
official/core/train_lib_test.py
official/core/train_utils.py
official/core/train_utils_test.py
official/legacy/__init__.py
official/legacy/albert/__init__.py
official/legacy/albert/configs.py
official/legacy/bert/__init__.py
official/legacy/bert/bert_models.py
official/legacy/bert/bert_models_test.py
official/legacy/bert/common_flags.py
official/legacy/bert/configs.py
official/legacy/bert/export_tfhub.py
official/legacy/bert/export_tfhub_test.py
official/legacy/bert/input_pipeline.py
official/legacy/bert/model_saving_utils.py
official/legacy/bert/model_training_utils.py
official/legacy/bert/model_training_utils_test.py
official/legacy/bert/run_classifier.py
official/legacy/bert/run_pretraining.py
official/legacy/bert/run_squad.py
official/legacy/bert/run_squad_helper.py
official/legacy/bert/serving.py
official/legacy/detection/__init__.py
official/legacy/detection/main.py
official/legacy/detection/configs/__init__.py
tf_models_no_deps-2.19.0.dist-info/AUTHORS
tf_models_no_deps-2.19.0.dist-info/LICENSE
tf_models_no_deps-2.19.0.dist-info/METADATA
tf_models_no_deps-2.19.0.dist-info/WHEEL
tf_models_no_deps-2.19.0.dist-info/top_level.txt
tf_models_no_deps-2.19.0.dist-info/RECORD
